alibabacloud_vs20181212/__init__.py
alibabacloud_vs20181212/client.py
alibabacloud_vs20181212/models/__init__.py
alibabacloud_vs20181212/models/_add_vs_pull_stream_info_config_request.py
alibabacloud_vs20181212/models/_add_vs_pull_stream_info_config_response.py
alibabacloud_vs20181212/models/_add_vs_pull_stream_info_config_response_body.py
alibabacloud_vs20181212/models/_associate_rendering_project_instances_request.py
alibabacloud_vs20181212/models/_associate_rendering_project_instances_response.py
alibabacloud_vs20181212/models/_associate_rendering_project_instances_response_body.py
alibabacloud_vs20181212/models/_associate_rendering_project_instances_shrink_request.py
alibabacloud_vs20181212/models/_batch_bind_directories_request.py
alibabacloud_vs20181212/models/_batch_bind_directories_response.py
alibabacloud_vs20181212/models/_batch_bind_directories_response_body.py
alibabacloud_vs20181212/models/_batch_bind_parent_platform_devices_request.py
alibabacloud_vs20181212/models/_batch_bind_parent_platform_devices_response.py
alibabacloud_vs20181212/models/_batch_bind_parent_platform_devices_response_body.py
alibabacloud_vs20181212/models/_batch_bind_purchased_devices_request.py
alibabacloud_vs20181212/models/_batch_bind_purchased_devices_response.py
alibabacloud_vs20181212/models/_batch_bind_purchased_devices_response_body.py
alibabacloud_vs20181212/models/_batch_bind_template_request.py
alibabacloud_vs20181212/models/_batch_bind_template_response.py
alibabacloud_vs20181212/models/_batch_bind_template_response_body.py
alibabacloud_vs20181212/models/_batch_bind_templates_request.py
alibabacloud_vs20181212/models/_batch_bind_templates_response.py
alibabacloud_vs20181212/models/_batch_bind_templates_response_body.py
alibabacloud_vs20181212/models/_batch_delete_devices_request.py
alibabacloud_vs20181212/models/_batch_delete_devices_response.py
alibabacloud_vs20181212/models/_batch_delete_devices_response_body.py
alibabacloud_vs20181212-3.6.0.dist-info/LICENSE
alibabacloud_vs20181212-3.6.0.dist-info/METADATA
alibabacloud_vs20181212-3.6.0.dist-info/WHEEL
alibabacloud_vs20181212-3.6.0.dist-info/top_level.txt
alibabacloud_vs20181212-3.6.0.dist-info/RECORD
